{
	"name": "sample",
	"frames_per_state": 3,
	"group": {
		"mob": {
			"row": 1,
			"entity": ["mob1", "mob2"],
			"state": ["enter", "north", "east", "south", "west", "damaged", "dying", "finish"]
		},
		"tower": {
			"row": 4,
			"entity": ["tower1", "tower2"],
			"state": ["enter", "north", "east", "south", "west", "idle", "leave"]
		},
		"lava": {
			"row": 7,
			"entity": ["normal"],
			"state": ["idle","opening","opened"]
		},
		"scene": {
			"row": 9,
			"entity": ["wall","furniture","floor"],
			"state": ["idle"]
		}
	}
}
